csvgen/__init__.py
csvgen/__main__.py
csvgen/program/__init__.py
csvgen/program/csvgen.py
csvgen/program/settings.py
csvgen/program/data/__init__.py
csvgen/program/data/all.last.txt
csvgen/program/data/cities.txt
csvgen/program/data/data_read_me.txt
csvgen/program/data/female.first.txt
csvgen/program/data/male.first.txt
csvgen/program/data/places.txt
csvgen/program/data/suffixes.txt
csvgen/program/data/words.txt
csvgen/program/data/zip.codes.txt
csvgen/program/docs/__init__.py
csvgen/program/docs/help.txt
csvgen/program/docs/man.txt
csvgen/program/generators/__init__.py
csvgen/program/generators/address.py
csvgen/program/generators/csv.py
csvgen/program/generators/loader.py
csvgen/program/generators/randomize.py
csvgen/program/models/__init__.py
csvgen/program/models/model.py
csvgen/program/output/output.txt
csvgen/program/output/readme.txt
csvgen-1.0.0.dist-info/DESCRIPTION.rst
csvgen-1.0.0.dist-info/METADATA
csvgen-1.0.0.dist-info/RECORD
csvgen-1.0.0.dist-info/WHEEL
csvgen-1.0.0.dist-info/entry_points.txt
csvgen-1.0.0.dist-info/metadata.json
csvgen-1.0.0.dist-info/top_level.txt
