Metadata-Version: 2.0
Name: csvgen
Version: 1.0.0
Summary: A command line CSV data output generator for testing
Home-page: https://www.adamyork.com
Author: Adam York
Author-email: adam@adamyork.com
License: MIT
Project-URL: AdamYork.com, https://www.adamyork.com
Project-URL: GitHub, https://github.com/yorkadam
Keywords: software development text processing testing
Platform: LINUX
Platform: UBUNTU 16+
Platform: OSX 9+
Platform: BSD
Platform: WIN10
Classifier: Development Status :: 4 - Beta
Classifier: Intended Audience :: Developers
Classifier: Topic :: Software Development :: Testing
Classifier: Topic :: Text Processing :: General
Classifier: License :: OSI Approved :: MIT License
Classifier: Natural Language :: English
Classifier: Operating System :: Microsoft :: Windows :: Windows 10
Classifier: Operating System :: POSIX :: Linux
Classifier: Operating System :: MacOS
Classifier: Programming Language :: Python :: 3.6
Classifier: Programming Language :: Python :: 3
Classifier: Programming Language :: Python :: 3.2
Classifier: Programming Language :: Python :: 3.3
Classifier: Programming Language :: Python :: 3.4
Requires-Python: >=3
